easycheck_doiteasy/__init__.py
easycheck_doiteasy/easycheck_doiteasy.py
easycheck_doiteasy-0.1.1.dist-info/LICENSE.txt
easycheck_doiteasy-0.1.1.dist-info/METADATA
easycheck_doiteasy-0.1.1.dist-info/WHEEL
easycheck_doiteasy-0.1.1.dist-info/top_level.txt
easycheck_doiteasy-0.1.1.dist-info/RECORD
