Metadata-Version: 2.1
Name: easycheck-doiteasy
Version: 0.1.1
Summary: A simple Python package example
Home-page: https://etlcheck.com/
Author: Jesus Rojas
Author-email: jora2415@gmailc.om
Project-URL: Bug Tracker, https://github.com/kamicase24/easycheck/-/issues
Project-URL: repository, https://github.com/kamicase24/easycheck
Classifier: Programming Language :: Python :: 3
Classifier: License :: OSI Approved :: MIT License
Classifier: Operating System :: OS Independent
License-File: LICENSE.txt
